information_extractor/__init__.py
information_extractor/dependencies.py
information_extractor/main.py
information_extractor/iecode/__init__.py
information_extractor/iecode/rel_extractor.py
information_extractor/iecode/spanbert.py
information_extractor/iecode/pytorch_pretrained_bert/__init__.py
information_extractor/iecode/pytorch_pretrained_bert/file_utils.py
information_extractor/iecode/pytorch_pretrained_bert/modeling.py
information_extractor/iecode/pytorch_pretrained_bert/optimization.py
information_extractor/iecode/pytorch_pretrained_bert/tokenization.py
information_extractor-0.2.0.dist-info/METADATA
information_extractor-0.2.0.dist-info/WHEEL
information_extractor-0.2.0.dist-info/entry_points.txt
information_extractor-0.2.0.dist-info/top_level.txt
information_extractor-0.2.0.dist-info/RECORD
