Metadata-Version: 2.4
Name: information_extractor
Version: 0.2.0
Summary: Information extractor using spaCy + SpanBERT
Home-page: https://github.com/rajatasusual/information_extractor
Author: Rajatasusual
Author-email: krajat4@gmail.com
License: MIT
Classifier: Programming Language :: Python :: 3
Classifier: License :: OSI Approved :: MIT License
Classifier: Operating System :: OS Independent
Requires-Python: >=3.6
Requires-Dist: annotated-types==0.7.0
Requires-Dist: blis==0.7.11
Requires-Dist: catalogue==2.0.10
Requires-Dist: certifi==2025.1.31
Requires-Dist: charset-normalizer==3.4.1
Requires-Dist: click==8.1.8
Requires-Dist: cloudpathlib==0.21.0
Requires-Dist: confection==0.1.5
Requires-Dist: coreferee==1.4.1
Requires-Dist: cymem==2.0.11
Requires-Dist: filelock==3.13.1
Requires-Dist: fsspec==2024.6.1
Requires-Dist: idna==3.10
Requires-Dist: Jinja2==3.1.6
Requires-Dist: langcodes==3.5.0
Requires-Dist: language_data==1.3.0
Requires-Dist: marisa-trie==1.2.1
Requires-Dist: markdown-it-py==3.0.0
Requires-Dist: MarkupSafe==3.0.2
Requires-Dist: mdurl==0.1.2
Requires-Dist: mpmath==1.3.0
Requires-Dist: murmurhash==1.0.12
Requires-Dist: networkx==3.3
Requires-Dist: numpy==1.26.4
Requires-Dist: packaging==24.2
Requires-Dist: pathlib_abc==0.1.1
Requires-Dist: pathy==0.11.0
Requires-Dist: pillow==11.0.0
Requires-Dist: preshed==3.0.9
Requires-Dist: psutil==7.0.0
Requires-Dist: pydantic==1.10.21
Requires-Dist: pydantic_core==2.33.1
Requires-Dist: Pygments==2.19.1
Requires-Dist: requests==2.32.3
Requires-Dist: rich==14.0.0
Requires-Dist: scipy==1.15.2
Requires-Dist: shellingham==1.5.4
Requires-Dist: smart-open==6.4.0
Requires-Dist: spacy==3.5.4
Requires-Dist: spacy-legacy==3.0.12
Requires-Dist: spacy-loggers==1.0.5
Requires-Dist: srsly==2.5.1
Requires-Dist: sympy==1.13.1
Requires-Dist: thinc==8.1.12
Requires-Dist: tqdm==4.67.1
Requires-Dist: typer==0.9.4
Requires-Dist: typing-inspection==0.4.0
Requires-Dist: typing_extensions==4.13.2
Requires-Dist: urllib3==2.4.0
Requires-Dist: wasabi==1.1.3
Requires-Dist: weasel==0.4.1
Requires-Dist: wrapt==1.17.2
